accuralai_ollama/__init__.py
accuralai_ollama/backend.py
accuralai_ollama-0.2.1.dist-info/METADATA
accuralai_ollama-0.2.1.dist-info/WHEEL
accuralai_ollama-0.2.1.dist-info/entry_points.txt
accuralai_ollama-0.2.1.dist-info/licenses/LICENSE
accuralai_ollama-0.2.1.dist-info/RECORD
