Metadata-Version: 2.4
Name: accuralai-ollama
Version: 0.2.1
Summary: Ollama backend adapter for the AccuralAI LLM orchestration pipeline.
Project-URL: homepage, https://accural-ai.web.app/
Project-URL: repository, https://github.com/AccuralAI/accuralai-ollama
Project-URL: documentation, https://accuralai.readthedocs.io/en/latest/packages/accuralai-ollama/index.html
Author: AccuralAI Maintainers
License: Apache-2.0
License-File: LICENSE
Requires-Python: >=3.10
Requires-Dist: accuralai-core
Requires-Dist: httpx>=0.27
Requires-Dist: pydantic>=2.5
Provides-Extra: dev
Requires-Dist: pytest; extra == 'dev'
Requires-Dist: pytest-anyio; extra == 'dev'
Requires-Dist: pytest-mock; extra == 'dev'
